LICENSE.txt
MANIFEST.in
README.rst
setup.py
PyFDE.egg-info/PKG-INFO
PyFDE.egg-info/SOURCES.txt
PyFDE.egg-info/dependency_links.txt
PyFDE.egg-info/requires.txt
PyFDE.egg-info/top_level.txt
docs/Makefile
docs/conf.py
docs/index.rst
docs/make.bat
docs/performance.rst
docs/reference.rst
docs/tutorial.rst
pyfde/__init__.py
pyfde/bench.c
pyfde/bench.pyx
pyfde/classicde.c
pyfde/classicde.pyx
pyfde/jade.c
pyfde/jade.pyx
pyfde/rng.c
pyfde/rng.pyx
tests/__init__.py
tests/ackley.py
tests/benchmark.py
tests/generator.py
tests/perf.py
tests/pyfde_test.py
tests/rastrigin.py
tests/schewefel.py