Metadata-Version: 1.1
Name: PyFDE
Version: 1.3.0
Summary: A fast differential evolution module
Home-page: https://bitbucket.org/lucashnegri/pyfde
Author: Lucas Hermann Negri
Author-email: lucashnegri@gmail.com
License: MIT
Keywords: differential evolution search optimization evolutionary
Platform: UNKNOWN
Classifier: Development Status :: 5 - Production/Stable
Classifier: License :: OSI Approved :: MIT License
Classifier: Programming Language :: Cython
Classifier: Programming Language :: Python
Classifier: Programming Language :: Python :: 3
Classifier: Topic :: Scientific/Engineering :: Artificial Intelligence
